<?xml version='1.0'?>
<ns2:test-suite xmlns:ns2='urn:model.allure.qatools.yandex.ru' start='1613932289967' stop='1613932309771'>
    <name>UI тесты для сайта https://www.themoviedb.org, роль - пользователь:</name>
    <title>UI тесты для сайта https://www.themoviedb.org, роль - пользователь:</title>
    <test-cases>
        <test-case start='1613932289968' status='passed' stop='1613932292484'>
            <name>1. Пользователь может авторизоваться</name>
            <title>1. Пользователь может авторизоваться</title>
            <labels/>
            <parameters/>
            <steps>
                <step start='1613932289970' status='passed' stop='1613932292224'>
                    <name>loginPage: login "Fox.red", "q12345"</name>
                    <title>loginPage: login "Fox.red", "q12345"</title>
                    <attachments/>
                    <steps>
                        <step start='1613932289970' status='passed' stop='1613932290476'>
                            <name>I am on page "https://www.themoviedb.org"</name>
                            <title>I am on page "https://www.themoviedb.org"</title>
                            <attachments/>
                            <steps/>
                        </step>
                        <step start='1613932290476' status='passed' stop='1613932290485'>
                            <name>I wait for element {"css":"body > div.page_wrap._wrap > header > div.content > div > div.flex > ul > li:nth-child(3) > a"}, 5</name>
                            <title>I wait for element {"css":"body > div.page_wrap._wrap > header > div.content > div > div.flex > ul > li:nth-child(3) > a"}, 5</title>
                            <attachments/>
                            <steps/>
                        </step>
                        <step start='1613932290485' status='passed' stop='1613932290862'>
                            <name>I click {"css":"body > div.page_wrap._wrap > header > div.content > div > div.flex > ul > li:nth-child(3) > a"}</name>
                            <title>I click {"css":"body > div.page_wrap._wrap > header > div.content > div > div.flex > ul > li:nth-child(3) > a"}</title>
                            <attachments/>
                            <steps/>
                        </step>
                        <step start='1613932290862' status='passed' stop='1613932290878'>
                            <name>I wait for element "#username", 10</name>
                            <title>I wait for element "#username", 10</title>
                            <attachments/>
                            <steps/>
                        </step>
                        <step start='1613932290879' status='passed' stop='1613932291027'>
                            <name>I click "#username"</name>
                            <title>I click "#username"</title>
                            <attachments/>
                            <steps/>
                        </step>
                        <step start='1613932291027' status='passed' stop='1613932291236'>
                            <name>I fill field "#username", "Fox.red"</name>
                            <title>I fill field "#username", "Fox.red"</title>
                            <attachments/>
                            <steps/>
                        </step>
                        <step start='1613932291236' status='passed' stop='1613932291360'>
                            <name>I click "#password"</name>
                            <title>I click "#password"</title>
                            <attachments/>
                            <steps/>
                        </step>
                        <step start='1613932291360' status='passed' stop='1613932291547'>
                            <name>I fill field "#password", "q12345"</name>
                            <title>I fill field "#password", "q12345"</title>
                            <attachments/>
                            <steps/>
                        </step>
                        <step start='1613932291547' status='passed' stop='1613932292224'>
                            <name>I click {"css":"#login_button"}</name>
                            <title>I click {"css":"#login_button"}</title>
                            <attachments/>
                            <steps/>
                        </step>
                    </steps>
                </step>
                <step start='1613932292224' status='passed' stop='1613932292483'>
                    <name>I see "Fox.red"</name>
                    <title>I see "Fox.red"</title>
                    <attachments/>
                    <steps/>
                </step>
            </steps>
            <attachments/>
        </test-case>
        <test-case start='1613932292490' status='passed' stop='1613932297451'>
            <name>2. Пользователь может добавить фильм в избранное</name>
            <title>2. Пользователь может добавить фильм в избранное</title>
            <labels/>
            <parameters/>
            <steps>
                <step start='1613932292492' status='passed' stop='1613932294990'>
                    <name>loginPage: login "Fox.red", "q12345"</name>
                    <title>loginPage: login "Fox.red", "q12345"</title>
                    <attachments/>
                    <steps>
                        <step start='1613932292492' status='passed' stop='1613932293107'>
                            <name>I am on page "https://www.themoviedb.org"</name>
                            <title>I am on page "https://www.themoviedb.org"</title>
                            <attachments/>
                            <steps/>
                        </step>
                        <step start='1613932293107' status='passed' stop='1613932293115'>
                            <name>I wait for element {"css":"body > div.page_wrap._wrap > header > div.content > div > div.flex > ul > li:nth-child(3) > a"}, 5</name>
                            <title>I wait for element {"css":"body > div.page_wrap._wrap > header > div.content > div > div.flex > ul > li:nth-child(3) > a"}, 5</title>
                            <attachments/>
                            <steps/>
                        </step>
                        <step start='1613932293115' status='passed' stop='1613932293480'>
                            <name>I click {"css":"body > div.page_wrap._wrap > header > div.content > div > div.flex > ul > li:nth-child(3) > a"}</name>
                            <title>I click {"css":"body > div.page_wrap._wrap > header > div.content > div > div.flex > ul > li:nth-child(3) > a"}</title>
                            <attachments/>
                            <steps/>
                        </step>
                        <step start='1613932293480' status='passed' stop='1613932293490'>
                            <name>I wait for element "#username", 10</name>
                            <title>I wait for element "#username", 10</title>
                            <attachments/>
                            <steps/>
                        </step>
                        <step start='1613932293490' status='passed' stop='1613932293627'>
                            <name>I click "#username"</name>
                            <title>I click "#username"</title>
                            <attachments/>
                            <steps/>
                        </step>
                        <step start='1613932293627' status='passed' stop='1613932293825'>
                            <name>I fill field "#username", "Fox.red"</name>
                            <title>I fill field "#username", "Fox.red"</title>
                            <attachments/>
                            <steps/>
                        </step>
                        <step start='1613932293826' status='passed' stop='1613932293962'>
                            <name>I click "#password"</name>
                            <title>I click "#password"</title>
                            <attachments/>
                            <steps/>
                        </step>
                        <step start='1613932293962' status='passed' stop='1613932294158'>
                            <name>I fill field "#password", "q12345"</name>
                            <title>I fill field "#password", "q12345"</title>
                            <attachments/>
                            <steps/>
                        </step>
                        <step start='1613932294158' status='passed' stop='1613932294990'>
                            <name>I click {"css":"#login_button"}</name>
                            <title>I click {"css":"#login_button"}</title>
                            <attachments/>
                            <steps/>
                        </step>
                    </steps>
                </step>
                <step start='1613932294990' status='passed' stop='1613932296523'>
                    <name>mainPage: search "Девушка, которая боялась дождя"</name>
                    <title>mainPage: search "Девушка, которая боялась дождя"</title>
                    <attachments/>
                    <steps>
                        <step start='1613932294990' status='passed' stop='1613932295544'>
                            <name>I am on page "https://www.themoviedb.org"</name>
                            <title>I am on page "https://www.themoviedb.org"</title>
                            <attachments/>
                            <steps/>
                        </step>
                        <step start='1613932295544' status='passed' stop='1613932296020'>
                            <name>I fill field "#inner_search_v4", "Девушка, которая боялась дождя"</name>
                            <title>I fill field "#inner_search_v4", "Девушка, которая боялась дождя"</title>
                            <attachments/>
                            <steps/>
                        </step>
                        <step start='1613932296020' status='passed' stop='1613932296500'>
                            <name>I click {"css":"#inner_search_form > input[type=submit]"}</name>
                            <title>I click {"css":"#inner_search_form > input[type=submit]"}</title>
                            <attachments/>
                            <steps/>
                        </step>
                        <step start='1613932296500' status='passed' stop='1613932296523'>
                            <name>I wait for element "#main > section > div > div > div.grey_column > div > h3", 5</name>
                            <title>I wait for element "#main > section > div > div > div.grey_column > div > h3", 5</title>
                            <attachments/>
                            <steps/>
                        </step>
                    </steps>
                </step>
                <step start='1613932296523' status='passed' stop='1613932297451'>
                    <name>moviePage: addToFavorites </name>
                    <title>moviePage: addToFavorites </title>
                    <attachments/>
                    <steps>
                        <step start='1613932296523' status='passed' stop='1613932297146'>
                            <name>I click "#card_movie_5cca0faa0e0a2604b5ed2366 > div > div.details > div.wrapper > div > div > a > h2"</name>
                            <title>I click "#card_movie_5cca0faa0e0a2604b5ed2366 > div > div.details > div.wrapper > div > div > a > h2"</title>
                            <attachments/>
                            <steps/>
                        </step>
                        <step start='1613932297146' status='passed' stop='1613932297450'>
                            <name>I click {"css":"#favourite > span"}</name>
                            <title>I click {"css":"#favourite > span"}</title>
                            <attachments/>
                            <steps/>
                        </step>
                    </steps>
                </step>
            </steps>
            <attachments/>
        </test-case>
        <test-case start='1613932297459' status='passed' stop='1613932304537'>
            <name>3. Пользователь может оставить рецензию на фильм</name>
            <title>3. Пользователь может оставить рецензию на фильм</title>
            <labels/>
            <parameters/>
            <steps>
                <step start='1613932297460' status='passed' stop='1613932299748'>
                    <name>loginPage: login "Fox.red", "q12345"</name>
                    <title>loginPage: login "Fox.red", "q12345"</title>
                    <attachments/>
                    <steps>
                        <step start='1613932297460' status='passed' stop='1613932298046'>
                            <name>I am on page "https://www.themoviedb.org"</name>
                            <title>I am on page "https://www.themoviedb.org"</title>
                            <attachments/>
                            <steps/>
                        </step>
                        <step start='1613932298047' status='passed' stop='1613932298059'>
                            <name>I wait for element {"css":"body > div.page_wrap._wrap > header > div.content > div > div.flex > ul > li:nth-child(3) > a"}, 5</name>
                            <title>I wait for element {"css":"body > div.page_wrap._wrap > header > div.content > div > div.flex > ul > li:nth-child(3) > a"}, 5</title>
                            <attachments/>
                            <steps/>
                        </step>
                        <step start='1613932298059' status='passed' stop='1613932298428'>
                            <name>I click {"css":"body > div.page_wrap._wrap > header > div.content > div > div.flex > ul > li:nth-child(3) > a"}</name>
                            <title>I click {"css":"body > div.page_wrap._wrap > header > div.content > div > div.flex > ul > li:nth-child(3) > a"}</title>
                            <attachments/>
                            <steps/>
                        </step>
                        <step start='1613932298428' status='passed' stop='1613932298439'>
                            <name>I wait for element "#username", 10</name>
                            <title>I wait for element "#username", 10</title>
                            <attachments/>
                            <steps/>
                        </step>
                        <step start='1613932298439' status='passed' stop='1613932298578'>
                            <name>I click "#username"</name>
                            <title>I click "#username"</title>
                            <attachments/>
                            <steps/>
                        </step>
                        <step start='1613932298578' status='passed' stop='1613932298781'>
                            <name>I fill field "#username", "Fox.red"</name>
                            <title>I fill field "#username", "Fox.red"</title>
                            <attachments/>
                            <steps/>
                        </step>
                        <step start='1613932298781' status='passed' stop='1613932298909'>
                            <name>I click "#password"</name>
                            <title>I click "#password"</title>
                            <attachments/>
                            <steps/>
                        </step>
                        <step start='1613932298909' status='passed' stop='1613932299096'>
                            <name>I fill field "#password", "q12345"</name>
                            <title>I fill field "#password", "q12345"</title>
                            <attachments/>
                            <steps/>
                        </step>
                        <step start='1613932299096' status='passed' stop='1613932299748'>
                            <name>I click {"css":"#login_button"}</name>
                            <title>I click {"css":"#login_button"}</title>
                            <attachments/>
                            <steps/>
                        </step>
                    </steps>
                </step>
                <step start='1613932299748' status='passed' stop='1613932304522'>
                    <name>moviePage: addReview </name>
                    <title>moviePage: addReview </title>
                    <attachments/>
                    <steps>
                        <step start='1613932299748' status='passed' stop='1613932300793'>
                            <name>I am on page "https://www.themoviedb.org/tv/1622-supernatural"</name>
                            <title>I am on page "https://www.themoviedb.org/tv/1622-supernatural"</title>
                            <attachments/>
                            <steps/>
                        </step>
                        <step start='1613932300793' status='passed' stop='1613932300956'>
                            <name>I click {"css":"#reviews"}</name>
                            <title>I click {"css":"#reviews"}</title>
                            <attachments/>
                            <steps/>
                        </step>
                        <step start='1613932300956' status='passed' stop='1613932303569'>
                            <name>I click {"css":"#media_v4 > div > div > div:nth-child(1) > div > section.panel.media_panel.social_panel.tv_panel > section > div.content > div > div > div > p > a"}</name>
                            <title>I click {"css":"#media_v4 > div > div > div:nth-child(1) > div > section.panel.media_panel.social_panel.tv_panel > section > div.content > div > div > div > p > a"}</title>
                            <attachments/>
                            <steps/>
                        </step>
                        <step start='1613932303569' status='passed' stop='1613932303983'>
                            <name>I fill field "#editor-textarea > div > textarea", "Its amazing! I like it."</name>
                            <title>I fill field "#editor-textarea > div > textarea", "Its amazing! I like it."</title>
                            <attachments/>
                            <steps/>
                        </step>
                        <step start='1613932303983' status='passed' stop='1613932304522'>
                            <name>I click {"css":"#submit"}</name>
                            <title>I click {"css":"#submit"}</title>
                            <attachments/>
                            <steps/>
                        </step>
                    </steps>
                </step>
                <step start='1613932304522' status='passed' stop='1613932304537'>
                    <name>I see "This review is currently awaiting moderator approval."</name>
                    <title>I see "This review is currently awaiting moderator approval."</title>
                    <attachments/>
                    <steps/>
                </step>
            </steps>
            <attachments/>
        </test-case>
        <test-case start='1613932304541' status='passed' stop='1613932309767'>
            <name>4. Пользователь может посмотреть свой список избранного</name>
            <title>4. Пользователь может посмотреть свой список избранного</title>
            <labels/>
            <parameters/>
            <steps>
                <step start='1613932304543' status='passed' stop='1613932307437'>
                    <name>loginPage: login "Fox.red", "q12345"</name>
                    <title>loginPage: login "Fox.red", "q12345"</title>
                    <attachments/>
                    <steps>
                        <step start='1613932304543' status='passed' stop='1613932305192'>
                            <name>I am on page "https://www.themoviedb.org"</name>
                            <title>I am on page "https://www.themoviedb.org"</title>
                            <attachments/>
                            <steps/>
                        </step>
                        <step start='1613932305192' status='passed' stop='1613932305204'>
                            <name>I wait for element {"css":"body > div.page_wrap._wrap > header > div.content > div > div.flex > ul > li:nth-child(3) > a"}, 5</name>
                            <title>I wait for element {"css":"body > div.page_wrap._wrap > header > div.content > div > div.flex > ul > li:nth-child(3) > a"}, 5</title>
                            <attachments/>
                            <steps/>
                        </step>
                        <step start='1613932305204' status='passed' stop='1613932305572'>
                            <name>I click {"css":"body > div.page_wrap._wrap > header > div.content > div > div.flex > ul > li:nth-child(3) > a"}</name>
                            <title>I click {"css":"body > div.page_wrap._wrap > header > div.content > div > div.flex > ul > li:nth-child(3) > a"}</title>
                            <attachments/>
                            <steps/>
                        </step>
                        <step start='1613932305573' status='passed' stop='1613932305594'>
                            <name>I wait for element "#username", 10</name>
                            <title>I wait for element "#username", 10</title>
                            <attachments/>
                            <steps/>
                        </step>
                        <step start='1613932305594' status='passed' stop='1613932305727'>
                            <name>I click "#username"</name>
                            <title>I click "#username"</title>
                            <attachments/>
                            <steps/>
                        </step>
                        <step start='1613932305727' status='passed' stop='1613932305926'>
                            <name>I fill field "#username", "Fox.red"</name>
                            <title>I fill field "#username", "Fox.red"</title>
                            <attachments/>
                            <steps/>
                        </step>
                        <step start='1613932305926' status='passed' stop='1613932306060'>
                            <name>I click "#password"</name>
                            <title>I click "#password"</title>
                            <attachments/>
                            <steps/>
                        </step>
                        <step start='1613932306060' status='passed' stop='1613932306249'>
                            <name>I fill field "#password", "q12345"</name>
                            <title>I fill field "#password", "q12345"</title>
                            <attachments/>
                            <steps/>
                        </step>
                        <step start='1613932306249' status='passed' stop='1613932307437'>
                            <name>I click {"css":"#login_button"}</name>
                            <title>I click {"css":"#login_button"}</title>
                            <attachments/>
                            <steps/>
                        </step>
                    </steps>
                </step>
                <step start='1613932307437' status='passed' stop='1613932308822'>
                    <name>mainPage: goToAccount </name>
                    <title>mainPage: goToAccount </title>
                    <attachments/>
                    <steps>
                        <step start='1613932307437' status='passed' stop='1613932308024'>
                            <name>I am on page "https://www.themoviedb.org"</name>
                            <title>I am on page "https://www.themoviedb.org"</title>
                            <attachments/>
                            <steps/>
                        </step>
                        <step start='1613932308024' status='passed' stop='1613932308030'>
                            <name>I wait for text "Привет, Fox.red!"</name>
                            <title>I wait for text "Привет, Fox.red!"</title>
                            <attachments/>
                            <steps/>
                        </step>
                        <step start='1613932308030' status='passed' stop='1613932308822'>
                            <name>I click {"css":"body > footer > nav > div.join > a"}</name>
                            <title>I click {"css":"body > footer > nav > div.join > a"}</title>
                            <attachments/>
                            <steps/>
                        </step>
                    </steps>
                </step>
                <step start='1613932308822' status='passed' stop='1613932309639'>
                    <name>accountPage: openFavorites </name>
                    <title>accountPage: openFavorites </title>
                    <attachments/>
                    <steps>
                        <step start='1613932308822' status='passed' stop='1613932308914'>
                            <name>I wait for text "Обзор"</name>
                            <title>I wait for text "Обзор"</title>
                            <attachments/>
                            <steps/>
                        </step>
                        <step start='1613932308914' status='passed' stop='1613932309084'>
                            <name>I click "//span[contains(text(), 'Обзор')]"</name>
                            <title>I click "//span[contains(text(), 'Обзор')]"</title>
                            <attachments/>
                            <steps/>
                        </step>
                        <step start='1613932309084' status='passed' stop='1613932309241'>
                            <name>I click "//span[contains(text(), 'Избранные')]"</name>
                            <title>I click "//span[contains(text(), 'Избранные')]"</title>
                            <attachments/>
                            <steps/>
                        </step>
                        <step start='1613932309241' status='passed' stop='1613932309639'>
                            <name>I click "//a[contains(@href, 'favorites') and contains(text(), 'Фильмы')]"</name>
                            <title>I click "//a[contains(@href, 'favorites') and contains(text(), 'Фильмы')]"</title>
                            <attachments/>
                            <steps/>
                        </step>
                    </steps>
                </step>
                <step start='1613932309639' status='passed' stop='1613932309767'>
                    <name>I see "Избранные"</name>
                    <title>I see "Избранные"</title>
                    <attachments/>
                    <steps/>
                </step>
            </steps>
            <attachments/>
        </test-case>
    </test-cases>
</ns2:test-suite>